persian_sa/__init__.py
persian_sa/persian_sa.py
persian_sa/data/preprocessingpipline.pkl
persian_sa/data/svmmodel.pkl
persian_sa-0.2.5.dist-info/LICENSE
persian_sa-0.2.5.dist-info/METADATA
persian_sa-0.2.5.dist-info/WHEEL
persian_sa-0.2.5.dist-info/top_level.txt
persian_sa-0.2.5.dist-info/RECORD
