Metadata-Version: 2.1
Name: persian-sa
Version: 0.2.5
Summary: Python Machine Learning based API to predict sentiment for Persian text.
Home-page: https://github.com/kasrahabib/persian-sentiment-analysis
Author: Mohammad Kasra Habib
Author-email: kasrahabib@gmail.com
License: UNKNOWN
Platform: UNKNOWN
Classifier: Topic :: Text Processing
Classifier: License :: OSI Approved :: MIT License
Classifier: Natural Language :: Persian
Classifier: Programming Language :: Python :: 2.7
Classifier: Programming Language :: Python :: 3.4
Classifier: Programming Language :: Python :: 3.5
Classifier: Programming Language :: Python :: 3.6
Classifier: Programming Language :: Python :: 3.7
Classifier: Programming Language :: Python :: 3.8
Requires-Dist: numpy (>=1.18.4)
Requires-Dist: scipy (>=1.4.1)
Requires-Dist: scikit-learn
